[
  {
    "slug": "anchovy",
    "name": "Anchovy",
    "imageName": "/item-images/fish/anchovy.png",
    "price": 200,
    "shadowSize": "2",
    "location": "Sea",
    "time": "4am - 9pm",
    "appearsInMonths": [
      "Jan",
      "Feb",
      "Mar",
      "Apr",
      "May",
      "Jun",
      "Jul",
      "Aug",
      "Sep",
      "Oct",
      "Nov",
      "Dec"
    ]
  },
  {
    "slug": "angelfish",
    "name": "Angelfish",
    "imageName": "/item-images/fish/angelfish.png",
    "price": 3000,
    "shadowSize": "2",
    "location": "River",
    "time": "4pm - 9am",
    "appearsInMonths": [
      "May",
      "Jun",
      "Jul",
      "Aug",
      "Sep",
      "Oct"
    ]
  },
  {
    "slug": "arapaima",
    "name": "Arapaima",
    "imageName": "/item-images/fish/arapaima.png",
    "price": 10000,
    "shadowSize": "6",
    "location": "River",
    "time": "4pm - 9am",
    "appearsInMonths": [
      "Jun",
      "Jul",
      "Aug",
      "Sep"
    ]
  },
  {
    "slug": "arowana",
    "name": "Arowana",
    "imageName": "/item-images/fish/arowana.png",
    "price": 10000,
    "shadowSize": "4",
    "location": "River",
    "time": "4pm - 9am",
    "appearsInMonths": [
      "Jun",
      "Jul",
      "Aug",
      "Sep"
    ]
  },
  {
    "slug": "barred-knifejaw",
    "name": "Barred knifejaw",
    "imageName": "/item-images/fish/barred-knifejaw.png",
    "price": 5000,
    "shadowSize": "3",
    "location": "Sea",
    "time": "All day",
    "appearsInMonths": [
      "Mar",
      "Apr",
      "May",
      "Jun",
      "Jul",
      "Aug",
      "Sep",
      "Oct",
      "Nov"
    ]
  },
  {
    "slug": "barreleye",
    "name": "Barreleye",
    "imageName": "/item-images/fish/barreleye.png",
    "price": 15000,
    "shadowSize": "2",
    "location": "Sea",
    "time": "9pm - 4am",
    "appearsInMonths": [
      "Jan",
      "Feb",
      "Mar",
      "Apr",
      "May",
      "Jun",
      "Jul",
      "Aug",
      "Sep",
      "Oct",
      "Nov",
      "Dec"
    ]
  },
  {
    "slug": "betta",
    "name": "Betta",
    "imageName": "/item-images/fish/betta.png",
    "price": 2500,
    "shadowSize": "2",
    "location": "River",
    "time": "9am - 4pm",
    "appearsInMonths": [
      "May",
      "Jun",
      "Jul",
      "Aug",
      "Sep",
      "Oct"
    ]
  },
  {
    "slug": "bitterling",
    "name": "Bitterling",
    "imageName": "/item-images/fish/bitterling.png",
    "price": 900,
    "shadowSize": "1",
    "location": "River",
    "time": "All day",
    "appearsInMonths": [
      "Jan",
      "Feb",
      "Mar",
      "Nov",
      "Dec"
    ]
  },
  {
    "slug": "black-bass",
    "name": "Black bass",
    "imageName": "/item-images/fish/black-bass.png",
    "price": 400,
    "shadowSize": "4",
    "location": "River",
    "time": "All day",
    "appearsInMonths": [
      "Jan",
      "Feb",
      "Mar",
      "Apr",
      "May",
      "Jun",
      "Jul",
      "Aug",
      "Sep",
      "Oct",
      "Nov",
      "Dec"
    ]
  },
  {
    "slug": "blowfish",
    "name": "Blowfish",
    "imageName": "/item-images/fish/blowfish.png",
    "price": 5000,
    "shadowSize": "3",
    "location": "Sea",
    "time": "9pm - 4am",
    "appearsInMonths": [
      "Jan",
      "Feb",
      "Nov",
      "Dec"
    ]
  },
  {
    "slug": "blue-marlin",
    "name": "Blue marlin",
    "imageName": "/item-images/fish/blue-marlin.png",
    "price": 10000,
    "shadowSize": "6",
    "location": "Pier",
    "time": "All day",
    "appearsInMonths": [
      "Jan",
      "Feb",
      "Mar",
      "Apr",
      "Jul",
      "Aug",
      "Sep",
      "Nov",
      "Dec"
    ]
  },
  {
    "slug": "bluegill",
    "name": "Bluegill",
    "imageName": "/item-images/fish/bluegill.png",
    "price": 180,
    "shadowSize": "2",
    "location": "River",
    "time": "9am - 4pm",
    "appearsInMonths": [
      "Jan",
      "Feb",
      "Mar",
      "Apr",
      "May",
      "Jun",
      "Jul",
      "Aug",
      "Sep",
      "Oct",
      "Nov",
      "Dec"
    ]
  },
  {
    "slug": "butterfly-fish",
    "name": "Butterfly fish",
    "imageName": "/item-images/fish/butterfly-fish.png",
    "price": 1000,
    "shadowSize": "2",
    "location": "Sea",
    "time": "All day",
    "appearsInMonths": [
      "Apr",
      "May",
      "Jun",
      "Jul",
      "Aug",
      "Sep"
    ]
  },
  {
    "slug": "carp",
    "name": "Carp",
    "imageName": "/item-images/fish/carp.png",
    "price": 300,
    "shadowSize": "4",
    "location": "Pond",
    "time": "All day",
    "appearsInMonths": [
      "Jan",
      "Feb",
      "Mar",
      "Apr",
      "May",
      "Jun",
      "Jul",
      "Aug",
      "Sep",
      "Oct",
      "Nov",
      "Dec"
    ]
  },
  {
    "slug": "catfish",
    "name": "Catfish",
    "imageName": "/item-images/fish/catfish.png",
    "price": 800,
    "shadowSize": "4",
    "location": "Pond",
    "time": "4pm - 9am",
    "appearsInMonths": [
      "May",
      "Jun",
      "Jul",
      "Aug",
      "Sep",
      "Oct"
    ]
  },
  {
    "slug": "char",
    "name": "Char",
    "imageName": "/item-images/fish/char.png",
    "price": 3800,
    "shadowSize": "3",
    "location": "River (Clifftop) Pond",
    "time": "4pm - 9am (Mar-Jun) All day (Sep-Nov)",
    "appearsInMonths": [
      "Mar",
      "Apr",
      "May",
      "Jun",
      "Sep",
      "Oct",
      "Nov"
    ]
  },
  {
    "slug": "cherry-salmon",
    "name": "Cherry salmon",
    "imageName": "/item-images/fish/cherry-salmon.png",
    "price": 1000,
    "shadowSize": "3",
    "location": "River (Clifftop)",
    "time": "4pm - 9am",
    "appearsInMonths": [
      "Mar",
      "Apr",
      "May",
      "Jun",
      "Sep",
      "Oct",
      "Nov"
    ]
  },
  {
    "slug": "clown-fish",
    "name": "Clown fish",
    "imageName": "/item-images/fish/clown-fish.png",
    "price": 650,
    "shadowSize": "1",
    "location": "Sea",
    "time": "All day",
    "appearsInMonths": [
      "Apr",
      "May",
      "Jun",
      "Jul",
      "Aug",
      "Sep"
    ]
  },
  {
    "slug": "coelacanth",
    "name": "Coelacanth",
    "imageName": "/item-images/fish/coelacanth.png",
    "price": 15000,
    "shadowSize": "6",
    "location": "Sea (Rain)",
    "time": "All day",
    "appearsInMonths": [
      "Jan",
      "Feb",
      "Mar",
      "Apr",
      "May",
      "Jun",
      "Jul",
      "Aug",
      "Sep",
      "Oct",
      "Nov",
      "Dec"
    ]
  },
  {
    "slug": "crawfish",
    "name": "Crawfish",
    "imageName": "/item-images/fish/crawfish.png",
    "price": 200,
    "shadowSize": "2",
    "location": "Pond",
    "time": "All day",
    "appearsInMonths": [
      "Apr",
      "May",
      "Jun",
      "Jul",
      "Aug",
      "Sep"
    ]
  },
  {
    "slug": "crucian-carp",
    "name": "Crucian carp",
    "imageName": "/item-images/fish/crucian-carp.png",
    "price": 160,
    "shadowSize": "2",
    "location": "River",
    "time": "All day",
    "appearsInMonths": [
      "Jan",
      "Feb",
      "Mar",
      "Apr",
      "May",
      "Jun",
      "Jul",
      "Aug",
      "Sep",
      "Oct",
      "Nov",
      "Dec"
    ]
  },
  {
    "slug": "dab",
    "name": "Dab",
    "imageName": "/item-images/fish/dab.png",
    "price": 300,
    "shadowSize": "3",
    "location": "Sea",
    "time": "All day",
    "appearsInMonths": [
      "Jan",
      "Feb",
      "Mar",
      "Apr",
      "Oct",
      "Nov",
      "Dec"
    ]
  },
  {
    "slug": "dace",
    "name": "Dace",
    "imageName": "/item-images/fish/dace.png",
    "price": 240,
    "shadowSize": "3",
    "location": "River",
    "time": "4pm - 9am",
    "appearsInMonths": [
      "Jan",
      "Feb",
      "Mar",
      "Apr",
      "May",
      "Jun",
      "Jul",
      "Aug",
      "Sep",
      "Oct",
      "Nov",
      "Dec"
    ]
  },
  {
    "slug": "dorado",
    "name": "Dorado",
    "imageName": "/item-images/fish/dorado.png",
    "price": 15000,
    "shadowSize": "5",
    "location": "River",
    "time": "4am - 9pm",
    "appearsInMonths": [
      "Jun",
      "Jul",
      "Aug",
      "Sep"
    ]
  },
  {
    "slug": "football-fish",
    "name": "Football fish",
    "imageName": "/item-images/fish/football-fish.png",
    "price": 2500,
    "shadowSize": "4",
    "location": "Sea",
    "time": "4pm - 9am",
    "appearsInMonths": [
      "Jan",
      "Feb",
      "Mar",
      "Nov",
      "Dec"
    ]
  },
  {
    "slug": "freshwater-goby",
    "name": "Freshwater goby",
    "imageName": "/item-images/fish/freshwater-goby.png",
    "price": 400,
    "shadowSize": "2",
    "location": "River",
    "time": "4pm - 9am",
    "appearsInMonths": [
      "Jan",
      "Feb",
      "Mar",
      "Apr",
      "May",
      "Jun",
      "Jul",
      "Aug",
      "Sep",
      "Oct",
      "Nov",
      "Dec"
    ]
  },
  {
    "slug": "frog",
    "name": "Frog",
    "imageName": "/item-images/fish/frog.png",
    "price": 120,
    "shadowSize": "2",
    "location": "Pond",
    "time": "All day",
    "appearsInMonths": [
      "May",
      "Jun",
      "Jul",
      "Aug"
    ]
  },
  {
    "slug": "gar",
    "name": "Gar",
    "imageName": "/item-images/fish/gar.png",
    "price": 6000,
    "shadowSize": "5",
    "location": "Pond",
    "time": "4pm - 9am",
    "appearsInMonths": [
      "Jun",
      "Jul",
      "Aug",
      "Sep"
    ]
  },
  {
    "slug": "giant-snakehead",
    "name": "Giant snakehead",
    "imageName": "/item-images/fish/giant-snakehead.png",
    "price": 5500,
    "shadowSize": "4",
    "location": "Pond",
    "time": "9am - 4pm",
    "appearsInMonths": [
      "Jun",
      "Jul",
      "Aug"
    ]
  },
  {
    "slug": "giant-trevally",
    "name": "Giant trevally",
    "imageName": "/item-images/fish/giant-trevally.png",
    "price": 4500,
    "shadowSize": "5",
    "location": "Pier",
    "time": "All day",
    "appearsInMonths": [
      "May",
      "Jun",
      "Jul",
      "Aug",
      "Sep",
      "Oct"
    ]
  },
  {
    "slug": "golden-trout",
    "name": "Golden trout",
    "imageName": "/item-images/fish/golden-trout.png",
    "price": 15000,
    "shadowSize": "3",
    "location": "River (Clifftop)",
    "time": "4pm - 9am",
    "appearsInMonths": [
      "Mar",
      "Apr",
      "May",
      "Sep",
      "Oct",
      "Nov"
    ]
  },
  {
    "slug": "goldfish",
    "name": "Goldfish",
    "imageName": "/item-images/fish/goldfish.png",
    "price": 1300,
    "shadowSize": "1",
    "location": "Pond",
    "time": "All day",
    "appearsInMonths": [
      "Jan",
      "Feb",
      "Mar",
      "Apr",
      "May",
      "Jun",
      "Jul",
      "Aug",
      "Sep",
      "Oct",
      "Nov",
      "Dec"
    ]
  },
  {
    "slug": "great-white-shark",
    "name": "Great white shark",
    "imageName": "/item-images/fish/great-white-shark.png",
    "price": 15000,
    "shadowSize": "6 (Fin)",
    "location": "Sea",
    "time": "4pm - 9am",
    "appearsInMonths": [
      "Jun",
      "Jul",
      "Aug",
      "Sep"
    ]
  },
  {
    "slug": "guppy",
    "name": "Guppy",
    "imageName": "/item-images/fish/guppy.png",
    "price": 1300,
    "shadowSize": "1",
    "location": "River",
    "time": "9am - 4pm",
    "appearsInMonths": [
      "Apr",
      "May",
      "Jun",
      "Jul",
      "Aug",
      "Sep",
      "Oct",
      "Nov"
    ]
  },
  {
    "slug": "hammerhead-shark",
    "name": "Hammerhead shark",
    "imageName": "/item-images/fish/hammerhead-shark.png",
    "price": 8000,
    "shadowSize": "6 (Fin)",
    "location": "Sea",
    "time": "4pm - 9am",
    "appearsInMonths": [
      "Jun",
      "Jul",
      "Aug",
      "Sep"
    ]
  },
  {
    "slug": "horse-mackerel",
    "name": "Horse mackerel",
    "imageName": "/item-images/fish/horse-mackerel.png",
    "price": 150,
    "shadowSize": "2",
    "location": "Sea",
    "time": "All day",
    "appearsInMonths": [
      "Jan",
      "Feb",
      "Mar",
      "Apr",
      "May",
      "Jun",
      "Jul",
      "Aug",
      "Sep",
      "Oct",
      "Nov",
      "Dec"
    ]
  },
  {
    "slug": "killifish",
    "name": "Killifish",
    "imageName": "/item-images/fish/killifish.png",
    "price": 300,
    "shadowSize": "1",
    "location": "Pond",
    "time": "All day",
    "appearsInMonths": [
      "Apr",
      "May",
      "Jun",
      "Jul",
      "Aug"
    ]
  },
  {
    "slug": "king-salmon",
    "name": "King salmon",
    "imageName": "/item-images/fish/king-salmon.png",
    "price": 1800,
    "shadowSize": "5",
    "location": "River (Mouth)",
    "time": "All day",
    "appearsInMonths": [
      "Sep"
    ]
  },
  {
    "slug": "koi",
    "name": "Koi",
    "imageName": "/item-images/fish/koi.png",
    "price": 4000,
    "shadowSize": "4",
    "location": "Pond",
    "time": "4pm - 9am",
    "appearsInMonths": [
      "Jan",
      "Feb",
      "Mar",
      "Apr",
      "May",
      "Jun",
      "Jul",
      "Aug",
      "Sep",
      "Oct",
      "Nov",
      "Dec"
    ]
  },
  {
    "slug": "loach",
    "name": "Loach",
    "imageName": "/item-images/fish/loach.png",
    "price": 400,
    "shadowSize": "2",
    "location": "River",
    "time": "All day",
    "appearsInMonths": [
      "Mar",
      "Apr",
      "May"
    ]
  },
  {
    "slug": "mahi-mahi",
    "name": "Mahi-mahi",
    "imageName": "/item-images/fish/mahi-mahi.png",
    "price": 6000,
    "shadowSize": "5",
    "location": "Pier",
    "time": "All day",
    "appearsInMonths": [
      "May",
      "Jun",
      "Jul",
      "Aug",
      "Sep",
      "Oct"
    ]
  },
  {
    "slug": "mitten-crab",
    "name": "Mitten crab",
    "imageName": "/item-images/fish/mitten-crab.png",
    "price": 2000,
    "shadowSize": "2",
    "location": "River",
    "time": "4pm - 9am",
    "appearsInMonths": [
      "Sep",
      "Oct",
      "Nov"
    ]
  },
  {
    "slug": "moray-eel",
    "name": "Moray eel",
    "imageName": "/item-images/fish/moray-eel.png",
    "price": 2000,
    "shadowSize": "Narrow",
    "location": "Sea",
    "time": "All day",
    "appearsInMonths": [
      "Aug",
      "Sep",
      "Oct"
    ]
  },
  {
    "slug": "napoleonfish",
    "name": "Napoleonfish",
    "imageName": "/item-images/fish/napoleonfish.png",
    "price": 10000,
    "shadowSize": "6",
    "location": "Sea",
    "time": "4am - 9pm",
    "appearsInMonths": [
      "Jul",
      "Aug"
    ]
  },
  {
    "slug": "neon-tetra",
    "name": "Neon tetra",
    "imageName": "/item-images/fish/neon-tetra.png",
    "price": 500,
    "shadowSize": "1",
    "location": "River",
    "time": "9am - 4pm",
    "appearsInMonths": [
      "Apr",
      "May",
      "Jun",
      "Jul",
      "Aug",
      "Sep",
      "Oct",
      "Nov"
    ]
  },
  {
    "slug": "nibble-fish",
    "name": "Nibble fish",
    "imageName": "/item-images/fish/nibble-fish.png",
    "price": 1500,
    "shadowSize": "1",
    "location": "River",
    "time": "9am - 4pm",
    "appearsInMonths": [
      "May",
      "Jun",
      "Jul",
      "Aug",
      "Sep"
    ]
  },
  {
    "slug": "oarfish",
    "name": "Oarfish",
    "imageName": "/item-images/fish/oarfish.png",
    "price": 9000,
    "shadowSize": "6",
    "location": "Sea",
    "time": "All day",
    "appearsInMonths": [
      "Jan",
      "Feb",
      "Mar",
      "Apr",
      "May",
      "Dec"
    ]
  },
  {
    "slug": "ocean-sunfish",
    "name": "Ocean sunfish",
    "imageName": "/item-images/fish/ocean-sunfish.png",
    "price": 4000,
    "shadowSize": "6 (Fin)",
    "location": "Sea",
    "time": "4am - 9pm",
    "appearsInMonths": [
      "Jul",
      "Aug",
      "Sep"
    ]
  },
  {
    "slug": "olive-flounder",
    "name": "Olive flounder",
    "imageName": "/item-images/fish/olive-flounder.png",
    "price": 800,
    "shadowSize": "5",
    "location": "Sea",
    "time": "All day",
    "appearsInMonths": [
      "Jan",
      "Feb",
      "Mar",
      "Apr",
      "May",
      "Jun",
      "Jul",
      "Aug",
      "Sep",
      "Oct",
      "Nov",
      "Dec"
    ]
  },
  {
    "slug": "pale-chub",
    "name": "Pale chub",
    "imageName": "/item-images/fish/pale-chub.png",
    "price": 200,
    "shadowSize": "1",
    "location": "River",
    "time": "9am - 4pm",
    "appearsInMonths": [
      "Jan",
      "Feb",
      "Mar",
      "Apr",
      "May",
      "Jun",
      "Jul",
      "Aug",
      "Sep",
      "Oct",
      "Nov",
      "Dec"
    ]
  },
  {
    "slug": "pike",
    "name": "Pike",
    "imageName": "/item-images/fish/pike.png",
    "price": 1800,
    "shadowSize": "5",
    "location": "River",
    "time": "All day",
    "appearsInMonths": [
      "Sep",
      "Oct",
      "Nov",
      "Dec"
    ]
  },
  {
    "slug": "piranha",
    "name": "Piranha",
    "imageName": "/item-images/fish/piranha.png",
    "price": 2500,
    "shadowSize": "2",
    "location": "River",
    "time": "9am - 4pm & 9pm - 4am",
    "appearsInMonths": [
      "Jun",
      "Jul",
      "Aug",
      "Sep"
    ]
  },
  {
    "slug": "pond-smelt",
    "name": "Pond smelt",
    "imageName": "/item-images/fish/pond-smelt.png",
    "price": 400,
    "shadowSize": "2",
    "location": "River",
    "time": "All day",
    "appearsInMonths": [
      "Jan",
      "Feb",
      "Dec"
    ]
  },
  {
    "slug": "pop-eyed-goldfish",
    "name": "Pop-eyed goldfish",
    "imageName": "/item-images/fish/pop-eyed-goldfish.png",
    "price": 1300,
    "shadowSize": "1",
    "location": "Pond",
    "time": "9am - 4pm",
    "appearsInMonths": [
      "Jan",
      "Feb",
      "Mar",
      "Apr",
      "May",
      "Jun",
      "Jul",
      "Aug",
      "Sep",
      "Oct",
      "Nov",
      "Dec"
    ]
  },
  {
    "slug": "puffer-fish",
    "name": "Puffer fish",
    "imageName": "/item-images/fish/puffer-fish.png",
    "price": 250,
    "shadowSize": "3",
    "location": "Sea",
    "time": "All day",
    "appearsInMonths": [
      "Jul",
      "Aug",
      "Sep"
    ]
  },
  {
    "slug": "rainbowfish",
    "name": "Rainbowfish",
    "imageName": "/item-images/fish/rainbowfish.png",
    "price": 800,
    "shadowSize": "1",
    "location": "River",
    "time": "9am - 4pm",
    "appearsInMonths": [
      "May",
      "Jun",
      "Jul",
      "Aug",
      "Sep",
      "Oct"
    ]
  },
  {
    "slug": "ranchu-goldfish",
    "name": "Ranchu goldfish",
    "imageName": "/item-images/fish/ranchu-goldfish.png",
    "price": 4500,
    "shadowSize": "2",
    "location": "Pond",
    "time": "9am - 4pm",
    "appearsInMonths": [
      "Jan",
      "Feb",
      "Mar",
      "Apr",
      "May",
      "Jun",
      "Jul",
      "Aug",
      "Sep",
      "Oct",
      "Nov",
      "Dec"
    ]
  },
  {
    "slug": "ray",
    "name": "Ray",
    "imageName": "/item-images/fish/ray.png",
    "price": 3000,
    "shadowSize": "5",
    "location": "Sea",
    "time": "4am - 9pm",
    "appearsInMonths": [
      "Aug",
      "Sep",
      "Oct",
      "Nov"
    ]
  },
  {
    "slug": "red-snapper",
    "name": "Red snapper",
    "imageName": "/item-images/fish/red-snapper.png",
    "price": 3000,
    "shadowSize": "4",
    "location": "Sea",
    "time": "All day",
    "appearsInMonths": [
      "Jan",
      "Feb",
      "Mar",
      "Apr",
      "May",
      "Jun",
      "Jul",
      "Aug",
      "Sep",
      "Oct",
      "Nov",
      "Dec"
    ]
  },
  {
    "slug": "ribbon-eel",
    "name": "Ribbon eel",
    "imageName": "/item-images/fish/ribbon-eel.png",
    "price": 600,
    "shadowSize": "Narrow",
    "location": "Sea",
    "time": "All day",
    "appearsInMonths": [
      "Jun",
      "Jul",
      "Aug",
      "Sep",
      "Oct"
    ]
  },
  {
    "slug": "saddled-bichir",
    "name": "Saddled bichir",
    "imageName": "/item-images/fish/saddled-bichir.png",
    "price": 4000,
    "shadowSize": "4",
    "location": "River",
    "time": "9pm - 4am",
    "appearsInMonths": [
      "Jun",
      "Jul",
      "Aug",
      "Sep"
    ]
  },
  {
    "slug": "salmon",
    "name": "Salmon",
    "imageName": "/item-images/fish/salmon.png",
    "price": 700,
    "shadowSize": "4",
    "location": "River (Mouth)",
    "time": "All day",
    "appearsInMonths": [
      "Sep"
    ]
  },
  {
    "slug": "saw-shark",
    "name": "Saw shark",
    "imageName": "/item-images/fish/saw-shark.png",
    "price": 12000,
    "shadowSize": "6 (Fin)",
    "location": "Sea",
    "time": "4pm - 9am",
    "appearsInMonths": [
      "Jun",
      "Jul",
      "Aug",
      "Sep"
    ]
  },
  {
    "slug": "sea-bass",
    "name": "Sea bass",
    "imageName": "/item-images/fish/sea-bass.png",
    "price": 400,
    "shadowSize": "5",
    "location": "Sea",
    "time": "All day",
    "appearsInMonths": [
      "Jan",
      "Feb",
      "Mar",
      "Apr",
      "May",
      "Jun",
      "Jul",
      "Aug",
      "Sep",
      "Oct",
      "Nov",
      "Dec"
    ]
  },
  {
    "slug": "sea-butterfly",
    "name": "Sea butterfly",
    "imageName": "/item-images/fish/sea-butterfly.png",
    "price": 1000,
    "shadowSize": "1",
    "location": "Sea",
    "time": "All day",
    "appearsInMonths": [
      "Jan",
      "Feb",
      "Mar",
      "Dec"
    ]
  },
  {
    "slug": "sea-horse",
    "name": "Sea horse",
    "imageName": "/item-images/fish/sea-horse.png",
    "price": 1100,
    "shadowSize": "1",
    "location": "Sea",
    "time": "All day",
    "appearsInMonths": [
      "Apr",
      "May",
      "Jun",
      "Jul",
      "Aug",
      "Sep",
      "Oct",
      "Nov"
    ]
  },
  {
    "slug": "snapping-turtle",
    "name": "Snapping Turtle",
    "imageName": "/item-images/fish/snapping-turtle.png",
    "price": 5000,
    "shadowSize": "4",
    "location": "River",
    "time": "9pm - 4am",
    "appearsInMonths": [
      "Apr",
      "May",
      "Jun",
      "Jul",
      "Aug",
      "Sep",
      "Oct"
    ]
  },
  {
    "slug": "soft-shelled-turtle",
    "name": "Soft-shelled turtle",
    "imageName": "/item-images/fish/soft-shelled-turtle.png",
    "price": 3750,
    "shadowSize": "4",
    "location": "River",
    "time": "4pm - 9am",
    "appearsInMonths": [
      "Aug",
      "Sep"
    ]
  },
  {
    "slug": "squid",
    "name": "Squid",
    "imageName": "/item-images/fish/squid.png",
    "price": 500,
    "shadowSize": "3",
    "location": "Sea",
    "time": "All day",
    "appearsInMonths": [
      "Jan",
      "Feb",
      "Mar",
      "Apr",
      "May",
      "Jun",
      "Jul",
      "Aug",
      "Dec"
    ]
  },
  {
    "slug": "stringfish",
    "name": "Stringfish",
    "imageName": "/item-images/fish/stringfish.png",
    "price": 15000,
    "shadowSize": "5",
    "location": "River (Clifftop)",
    "time": "4pm - 9am",
    "appearsInMonths": [
      "Jan",
      "Feb",
      "Mar",
      "Dec"
    ]
  },
  {
    "slug": "sturgeon",
    "name": "Sturgeon",
    "imageName": "/item-images/fish/sturgeon.png",
    "price": 10000,
    "shadowSize": "6",
    "location": "River (Mouth)",
    "time": "All day",
    "appearsInMonths": [
      "Jan",
      "Feb",
      "Mar",
      "Sep",
      "Oct",
      "Nov",
      "Dec"
    ]
  },
  {
    "slug": "suckerfish",
    "name": "Suckerfish",
    "imageName": "/item-images/fish/suckerfish.png",
    "price": 1500,
    "shadowSize": "6 (Fin)",
    "location": "Sea",
    "time": "All day",
    "appearsInMonths": [
      "Jun",
      "Jul",
      "Aug",
      "Sep"
    ]
  },
  {
    "slug": "surgeonfish",
    "name": "Surgeonfish",
    "imageName": "/item-images/fish/surgeonfish.png",
    "price": 1000,
    "shadowSize": "2",
    "location": "Sea",
    "time": "All day",
    "appearsInMonths": [
      "Apr",
      "May",
      "Jun",
      "Jul",
      "Aug",
      "Sep"
    ]
  },
  {
    "slug": "sweetfish",
    "name": "Sweetfish",
    "imageName": "/item-images/fish/sweetfish.png",
    "price": 900,
    "shadowSize": "3",
    "location": "River",
    "time": "All day",
    "appearsInMonths": [
      "Jul",
      "Aug",
      "Sep"
    ]
  },
  {
    "slug": "tadpole",
    "name": "Tadpole",
    "imageName": "/item-images/fish/tadpole.png",
    "price": 100,
    "shadowSize": "1",
    "location": "Pond",
    "time": "All day",
    "appearsInMonths": [
      "Mar",
      "Apr",
      "May",
      "Jun",
      "Jul"
    ]
  },
  {
    "slug": "tilapia",
    "name": "Tilapia",
    "imageName": "/item-images/fish/tilapia.png",
    "price": 800,
    "shadowSize": "3",
    "location": "River",
    "time": "All day",
    "appearsInMonths": [
      "Jun",
      "Jul",
      "Aug",
      "Sep",
      "Oct"
    ]
  },
  {
    "slug": "tuna",
    "name": "Tuna",
    "imageName": "/item-images/fish/tuna.png",
    "price": 7000,
    "shadowSize": "6",
    "location": "Pier",
    "time": "All day",
    "appearsInMonths": [
      "Jan",
      "Feb",
      "Mar",
      "Apr",
      "Nov",
      "Dec"
    ]
  },
  {
    "slug": "whale-shark",
    "name": "Whale shark",
    "imageName": "/item-images/fish/whale-shark.png",
    "price": 13000,
    "shadowSize": "6 (Fin)",
    "location": "Sea",
    "time": "All day",
    "appearsInMonths": [
      "Jun",
      "Jul",
      "Aug",
      "Sep"
    ]
  },
  {
    "slug": "yellow-perch",
    "name": "Yellow perch",
    "imageName": "/item-images/fish/yellow-perch.png",
    "price": 300,
    "shadowSize": "3",
    "location": "River",
    "time": "All day",
    "appearsInMonths": [
      "Jan",
      "Feb",
      "Mar",
      "Oct",
      "Nov",
      "Dec"
    ]
  },
  {
    "slug": "zebra-turkeyfish",
    "name": "Zebra turkeyfish",
    "imageName": "/item-images/fish/zebra-turkeyfish.png",
    "price": 500,
    "shadowSize": "3",
    "location": "Sea",
    "time": "All day",
    "appearsInMonths": [
      "Apr",
      "May",
      "Jun",
      "Jul",
      "Aug",
      "Sep",
      "Oct",
      "Nov"
    ]
  }
]